simplepytools/__init__.py
simplepytools/logmanager/__init__.py
simplepytools/logmanager/custom_logger.py
tests/__init__.py
tests/test_logmanager.py
SimplePyTools-0.1.0.dist-info/METADATA
SimplePyTools-0.1.0.dist-info/WHEEL
SimplePyTools-0.1.0.dist-info/top_level.txt
SimplePyTools-0.1.0.dist-info/RECORD
