Metadata-Version: 2.1
Name: SimplePyTools
Version: 0.1.0
Summary: A utility library for Python.
Home-page: https://github.com/simplehuman-engineering/sw-SimplePyTools
Author: Krishna Mandanapu
Author-email: kmandanapu@simplehuman.com
Classifier: Programming Language :: Python :: 3
Classifier: License :: OSI Approved :: MIT License
Classifier: Operating System :: OS Independent
Requires-Python: >=3.7
Requires-Dist: setuptools ==68.0.0
